{
    "name": "Category",
    "fields": [
        {
            "fieldName": "nameCategory",
            "fieldType": "String"
        },
        {
            "fieldName": "status",
            "fieldType": "Boolean"
        }
    ],
    "relationships": [
        {
            "relationshipType": "one-to-many",
            "otherEntityName": "product",
            "otherEntityRelationshipName": "category",
            "relationshipName": "product"
        }
    ],
    "changelogDate": "20210427150200",
    "entityTableName": "category",
    "dto": "no",
    "pagination": "infinite-scroll",
    "service": "serviceImpl",
    "jpaMetamodelFiltering": false,
    "fluentMethods": true,
    "readOnly": false,
    "embedded": false,
    "clientRootFolder": "",
    "applications": "*"
}